instigator_py/__init__.py
instigator_py/cli.py
instigator_py-0.3.0.dist-info/LICENSE
instigator_py-0.3.0.dist-info/METADATA
instigator_py-0.3.0.dist-info/WHEEL
instigator_py-0.3.0.dist-info/top_level.txt
instigator_py-0.3.0.dist-info/RECORD
