Metadata-Version: 2.1
Name: instigator_py
Version: 0.3.0
Summary: A boilerplate project generator
Author: Sachin
Author-email: Sachin <schnaror@gmail.com>
License: MIT
Project-URL: Homepage, https://about.me/sachin-arora
License-File: LICENSE
